{
"version": "9.82.9",
"downloadUrl": "https://github.com/khneifis123/-eklinics-releases/releases/download/v9.82.9/Inventra-Setup-9.82.9.exe",
"updateMode": "silent-internal-installer",
"userExperience": "background-download-then-silent-restart-update",
"commercialRule": "Inventra updates internally; users do not open GitHub, JSON, or choose files.",
"releaseNotes": [
"Safely changed Settings Data KPI cards to display 2 then 2 instead of 4 in one row.",
"Removed failed 9.82.8 and 9.82.8B layout attempts if present.",
"Added strict parent validation to avoid compressing the Settings page.",
"No SQL, app data, products, suppliers, orders, reports, inventory, or updater backend logic changed."
],
"publishedAt": "2026-06-21T09:20:00.000Z"
}
